{
  "title": "Linux Commands for Data Scientists",
  "description": "Basic Linux Commands",
  "difficulty": "beginner",
  "time": "10 minutes",
  "details": {
    "steps": [{
      "title": "Step 1 - Create and List Directory",
      "text": "step1.md"
    }],
    "intro": {
      "text": "intro.md",
      "credits": ""
    },
    "finish": {
      "text": "finish.md"
    }
  },
  "environment": {
    "uilayout": "terminal",
    "uimessage1": "\u001b[32mWelcome to Terminal Land!!.\r\n"
  },
  "backend": {
    "imageid": "bash"
  }
}